mrcrowbar/__init__.py
mrcrowbar/ansi.py
mrcrowbar/bits.py
mrcrowbar/blocks.py
mrcrowbar/checks.py
mrcrowbar/cli.py
mrcrowbar/colour.py
mrcrowbar/common.py
mrcrowbar/encoding.py
mrcrowbar/fields.py
mrcrowbar/loaders.py
mrcrowbar/models.py
mrcrowbar/refs.py
mrcrowbar/sound.py
mrcrowbar/statistics.py
mrcrowbar/tests.py
mrcrowbar/transforms.py
mrcrowbar/utils.py
mrcrowbar/version.py
mrcrowbar/views.py
mrcrowbar/lib/__init__.py
mrcrowbar/lib/audio/__init__.py
mrcrowbar/lib/audio/base.py
mrcrowbar/lib/audio/vgm.py
mrcrowbar/lib/audio/voc.py
mrcrowbar/lib/compressors/__init__.py
mrcrowbar/lib/compressors/lzss.py
mrcrowbar/lib/containers/__init__.py
mrcrowbar/lib/containers/mac.py
mrcrowbar/lib/containers/patch.py
mrcrowbar/lib/containers/riff.py
mrcrowbar/lib/games/__init__.py
mrcrowbar/lib/games/boppin.py
mrcrowbar/lib/games/deskadv.py
mrcrowbar/lib/games/jill.py
mrcrowbar/lib/games/keen.py
mrcrowbar/lib/games/lemmings.py
mrcrowbar/lib/games/lomax.py
mrcrowbar/lib/games/lostvikings.py
mrcrowbar/lib/games/presage.py
mrcrowbar/lib/games/sam.py
mrcrowbar/lib/games/sonic2.py
mrcrowbar/lib/games/supersolvers.py
mrcrowbar/lib/games/titus.py
mrcrowbar/lib/games/tyrian.py
mrcrowbar/lib/hardware/__init__.py
mrcrowbar/lib/hardware/ibm_pc.py
mrcrowbar/lib/hardware/megadrive.py
mrcrowbar/lib/images/__init__.py
mrcrowbar/lib/images/base.py
mrcrowbar/lib/os/__init__.py
mrcrowbar/lib/os/dos.py
mrcrowbar/lib/os/win16.py
mrcrowbar/lib/platforms/__init__.py
mrcrowbar/lib/platforms/clickteam.py
mrcrowbar/lib/platforms/director.py
mrcrowbar-0.9.0.dist-info/LICENSE
mrcrowbar-0.9.0.dist-info/METADATA
mrcrowbar-0.9.0.dist-info/WHEEL
mrcrowbar-0.9.0.dist-info/entry_points.txt
mrcrowbar-0.9.0.dist-info/top_level.txt
mrcrowbar-0.9.0.dist-info/RECORD
