Metadata-Version: 2.1
Name: mrcrowbar
Version: 0.9.0
Summary: A library and model framework for reverse engineering binary file formats
Home-page: https://moral.net.au/mrcrowbar
Author: Scott Percival
Author-email: code@moral.net.au
License: BSD
Platform: UNKNOWN
Classifier: Development Status :: 4 - Beta
Classifier: Environment :: Console
Classifier: Intended Audience :: Developers
Classifier: License :: OSI Approved :: BSD License
Classifier: Programming Language :: Python :: 3 :: Only
Classifier: Programming Language :: Python :: 3
Classifier: Programming Language :: Python :: 3.4
Classifier: Programming Language :: Python :: 3.5
Classifier: Programming Language :: Python :: 3.6
Classifier: Programming Language :: Python :: 3.7
Requires-Python: >=3
Provides-Extra: audio
Requires-Dist: pyaudio (>=0.2.9) ; extra == 'audio'
Provides-Extra: images
Requires-Dist: Pillow (>=2.8.1) ; extra == 'images'
